bingo/__init__.py
bingo/__main__.py
bingo/cli.py
bingo_cli-1.0.dist-info/LICENSE
bingo_cli-1.0.dist-info/METADATA
bingo_cli-1.0.dist-info/WHEEL
bingo_cli-1.0.dist-info/entry_points.txt
bingo_cli-1.0.dist-info/top_level.txt
bingo_cli-1.0.dist-info/RECORD
